letolt/__init__.py
letolt/letolt.py
letolt-0.4.dist-info/METADATA
letolt-0.4.dist-info/RECORD
letolt-0.4.dist-info/WHEEL
letolt-0.4.dist-info/top_level.txt
