Metadata-Version: 2.1
Name: letolt
Version: 0.4
Summary: Erettsegi letolto fuggveny 4 input alapjan.
Home-page: https://github.com/MatyiFKBT/letolt/
Author: Matyi
Author-email: mmatyi1999@gmail.com
License: UNKNOWN
Download-URL: https://github.com/MatyiFKBT/letolt/archive/0.1.tar.gz
Keywords: testing,erettsegi,letolt
Platform: UNKNOWN
Classifier: Programming Language :: Python :: 3
Classifier: License :: OSI Approved :: MIT License
Classifier: Operating System :: OS Independent
